{
  "version": 3,
  "lastUpdated": "2026-03-18",
  "words": {
    "verb": [
      {
        "lemma": "byť",
        "fr": "être",
        "conjugation": "ja som, ty si, on/ona je, my sme, vy ste, oni sú",
        "past": "bol/bola som, bol/bola si, bol/bola, boli sme, boli ste, boli",
        "example": "Som šťastný. = Je suis heureux.",
        "tip": "Le verbe #1 ! Irrégulier.",
        "box": 4,
        "reviews": 4,
        "errors": 0,
        "lastReview": 1773833838212
      },
      {
        "lemma": "mať",
        "fr": "avoir",
        "conjugation": "ja mám, ty máš, on/ona má, my máme, vy máte, oni majú",
        "past": "mal/mala som, mal/mala si, mal/mala, mali sme, mali ste, mali",
        "example": "Mám hlad. = J'ai faim.",
        "tip": "mať rád/rada = aimer",
        "box": 4,
        "reviews": 4,
        "errors": 0,
        "lastReview": 1773833842347
      },
      {
        "lemma": "chcieť",
        "fr": "vouloir",
        "conjugation": "ja chcem, ty chceš, on/ona chce, my chceme, vy chcete, oni chcú",
        "example": "Chcem ísť von. = Je veux sortir.",
        "tip": "Modal + infinitif",
        "box": 2,
        "reviews": 2,
        "errors": 0,
        "lastReview": 1773833847060
      },
      {
        "lemma": "robiť",
        "fr": "faire",
        "conjugation": "ja robím, ty robíš, on/ona robí, my robíme, vy robíte, oni robia",
        "example": "Čo robíš? = Tu fais quoi ?",
        "tip": "Question #1",
        "box": 1,
        "reviews": 2,
        "errors": 1,
        "_dir": "fr",
        "_prompt": "faire",
        "_correct": "robiť",
        "_mode": "plain",
        "lastReview": 1773833852858
      },
      {
        "lemma": "hovoriť",
        "fr": "parler",
        "conjugation": "ja hovorím, ty hovoríš, on/ona hovorí, my hovoríme, vy hovoríte, oni hovoria",
        "example": "Hovoríš po slovensky?",
        "tip": "hovoriť po + langue",
        "box": 1,
        "reviews": 3,
        "errors": 2,
        "lastReview": 1773833875826
      },
      {
        "lemma": "rozumieť",
        "fr": "comprendre",
        "conjugation": "ja rozumiem, ty rozumieš, on/ona rozumie, my rozumieme, vy rozumiete, oni rozumejú",
        "example": "Nerozumiem. = Je ne comprends pas.",
        "tip": "Phrase de survie #1",
        "box": 1,
        "reviews": 1,
        "errors": 0,
        "_dir": "sk",
        "_prompt": "rozumieť",
        "_correct": "comprendre",
        "_mode": "plain",
        "lastReview": 1773833746662
      },
      {
        "lemma": "milovať",
        "fr": "aimer (fort)",
        "conjugation": "ja milujem, ty miluješ, on/ona miluje, my milujeme, vy milujete, oni milujú",
        "example": "Milujem ťa. = Je t'aime.",
        "tip": "Pour ta copine !",
        "box": 0,
        "reviews": 1,
        "errors": 1,
        "lastReview": 1773833755814
      },
      {
        "lemma": "jesť",
        "fr": "manger",
        "conjugation": "ja jem, ty ješ, on/ona je, my jeme, vy jete, oni jedia",
        "example": "Chceš jesť? = Tu veux manger ?",
        "tip": "3e pers. 'je' = mange ET est !",
        "box": 1,
        "reviews": 1,
        "errors": 0,
        "lastReview": 1773833761978
      },
      {
        "lemma": "piť",
        "fr": "boire",
        "conjugation": "ja pijem, ty piješ, on/ona pije, my pijeme, vy pijete, oni pijú",
        "example": "Čo piješ? = Tu bois quoi ?",
        "tip": "piť kávu = boire un café",
        "box": 0,
        "reviews": 1,
        "errors": 1,
        "lastReview": 1773833770165
      },
      {
        "lemma": "vedieť",
        "fr": "savoir",
        "conjugation": "ja viem, ty vieš, on/ona vie, my vieme, vy viete, oni vedia",
        "example": "Neviem. = Je ne sais pas.",
        "tip": "Très courant",
        "box": 1,
        "reviews": 1,
        "errors": 0,
        "lastReview": 1773833781151
      },
      {
        "lemma": "môcť",
        "fr": "pouvoir",
        "conjugation": "ja môžem, ty môžeš, on/ona môže, my môžeme, vy môžete, oni môžu",
        "example": "Môžeme sa stretnúť? = On peut se voir ?",
        "tip": "Capacité / permission",
        "box": 1,
        "reviews": 1,
        "errors": 0,
        "lastReview": 1773833789270
      },
      {
        "lemma": "musieť",
        "fr": "devoir",
        "conjugation": "ja musím, ty musíš, on/ona musí, my musíme, vy musíte, oni musia",
        "example": "Musím ísť. = Je dois y aller.",
        "tip": "Obligation forte",
        "box": 0,
        "reviews": 1,
        "errors": 1,
        "_dir": "sk",
        "_prompt": "musieť",
        "_correct": "devoir",
        "_mode": "plain",
        "lastReview": 1773833791867
      },
      {
        "lemma": "prísť",
        "fr": "venir",
        "conjugation": "ja prídem, ty prídeš, on/ona príde, my prídeme, vy prídete, oni prídu",
        "example": "Kedy prídeš? = Quand viens-tu ?",
        "tip": "Perfectif de ísť",
        "box": 0,
        "reviews": 1,
        "errors": 1,
        "lastReview": 1773833794700
      },
      {
        "lemma": "dať",
        "fr": "donner",
        "conjugation": "ja dám, ty dáš, on/ona dá, my dáme, vy dáte, oni dajú",
        "example": "Daj mi vodu. = Donne-moi de l'eau.",
        "tip": "Impératif: daj!",
        "box": 1,
        "reviews": 1,
        "errors": 0,
        "lastReview": 1773833800533
      },
      {
        "lemma": "vidieť",
        "fr": "voir",
        "conjugation": "ja vidím, ty vidíš, on/ona vidí, my vidíme, vy vidíte, oni vidia",
        "example": "Vidíš to? = Tu vois ça ?",
        "tip": "vidieť sa = se voir",
        "box": 1,
        "reviews": 1,
        "errors": 0,
        "lastReview": 1773833805922
      },
      {
        "lemma": "pracovať",
        "fr": "travailler",
        "conjugation": "ja pracujem, ty pracuješ, on/ona pracuje, my pracujeme, vy pracujete, oni pracujú",
        "example": "Kde pracuješ? = Où travailles-tu ?",
        "tip": "práca = travail",
        "box": 1,
        "reviews": 1,
        "errors": 0,
        "lastReview": 1773833814551
      },
      {
        "lemma": "bývať",
        "fr": "habiter",
        "conjugation": "ja bývam, ty bývaš, on/ona býva, my bývame, vy bývate, oni bývajú",
        "example": "Kde bývaš? = Où habites-tu ?",
        "tip": "bývať v + ville",
        "box": 0,
        "reviews": 1,
        "errors": 1,
        "_dir": "sk",
        "_prompt": "bývať",
        "_correct": "habiter",
        "_mode": "plain",
        "lastReview": 1773833817319
      },
      {
        "lemma": "spať",
        "fr": "dormir",
        "conjugation": "ja spím, ty spíš, on/ona spí, my spíme, vy spíte, oni spia",
        "example": "Chcem spať. = Je veux dormir.",
        "tip": "spál/a = j'ai dormi",
        "box": 0,
        "reviews": 1,
        "errors": 1,
        "lastReview": 1773833820583
      },
      {
        "lemma": "čakať",
        "fr": "attendre",
        "conjugation": "ja čakám, ty čakáš, on/ona čaká, my čakáme, vy čakáte, oni čakajú",
        "example": "Čakaj! = Attends !",
        "tip": "Impératif: čakaj(te)!",
        "box": 0,
        "reviews": 1,
        "errors": 1,
        "lastReview": 1773833823551
      },
      {
        "lemma": "kupovať",
        "fr": "acheter",
        "conjugation": "ja kupujem, ty kupuješ, on/ona kupuje, my kupujeme, vy kupujete, oni kupujú",
        "example": "Čo kupuješ? = Qu'est-ce que tu achètes ?",
        "tip": "kúpiť = perfectif",
        "box": 0,
        "reviews": 1,
        "errors": 1,
        "lastReview": 1773833825636
      },
      {
        "lemma": "povedať",
        "fr": "dire",
        "conjugation": "ja poviem, ty povieš, on/ona povie, my povieme, vy poviete, oni povedia",
        "example": "Povieš mi? = Tu me diras ?",
        "tip": "Perfectif de hovoriť",
        "box": 0,
        "reviews": 1,
        "errors": 1,
        "lastReview": 1773833828319
      },
      {
        "lemma": "páčiť sa",
        "fr": "plaire",
        "conjugation": "páčim sa, páčiš sa, páči sa, páčime sa, páčite sa, páčia sa",
        "example": "Páči sa mi to. = Ça me plaît.",
        "tip": "Construction inversée",
        "box": 0,
        "reviews": 1,
        "errors": 1,
        "_dir": "fr",
        "_prompt": "plaire",
        "_correct": "páčiť sa",
        "_mode": "plain",
        "lastReview": 1773833831084
      }
    ],
    "noun": [
      {
        "lemma": "dom",
        "fr": "maison",
        "gender": "M",
        "plural": "domy",
        "example": "Ideme domov. = On rentre.",
        "tip": "domov = direction maison",
        "box": 0,
        "reviews": 0,
        "errors": 0
      },
      {
        "lemma": "žena",
        "fr": "femme",
        "gender": "F",
        "plural": "ženy",
        "example": "Tá žena je krásna.",
        "tip": "Aussi = épouse",
        "box": 0,
        "reviews": 0,
        "errors": 0
      },
      {
        "lemma": "muž",
        "fr": "homme/mari",
        "gender": "M",
        "plural": "muži",
        "example": "Ten muž je vysoký.",
        "tip": "Aussi = mari",
        "box": 0,
        "reviews": 0,
        "errors": 0,
        "_dir": "sk",
        "_prompt": "muž",
        "_correct": "homme/mari",
        "_mode": "plain"
      },
      {
        "lemma": "dieťa",
        "fr": "enfant",
        "gender": "N",
        "plural": "deti",
        "example": "Deti sa hrajú. = Les enfants jouent.",
        "tip": "Pluriel irrégulier !",
        "box": 0,
        "reviews": 0,
        "errors": 0
      },
      {
        "lemma": "jedlo",
        "fr": "nourriture",
        "gender": "N",
        "plural": "jedlá",
        "example": "Jedlo je dobré.",
        "tip": "jesť = manger",
        "box": 0,
        "reviews": 0,
        "errors": 0
      },
      {
        "lemma": "voda",
        "fr": "eau",
        "gender": "F",
        "plural": "vody",
        "example": "Daj mi vodu.",
        "tip": "Accusatif: vodu",
        "box": 0,
        "reviews": 0,
        "errors": 0
      },
      {
        "lemma": "pivo",
        "fr": "bière",
        "gender": "N",
        "plural": "pivá",
        "example": "Jedno pivo, prosím.",
        "tip": "Essentiel !",
        "box": 0,
        "reviews": 0,
        "errors": 0
      },
      {
        "lemma": "káva",
        "fr": "café",
        "gender": "F",
        "plural": "kávy",
        "example": "Dám si kávu.",
        "tip": "dám si = je prends",
        "box": 0,
        "reviews": 0,
        "errors": 0
      },
      {
        "lemma": "auto",
        "fr": "voiture",
        "gender": "N",
        "plural": "autá",
        "example": "Kde je auto?",
        "tip": "",
        "box": 0,
        "reviews": 0,
        "errors": 0,
        "_dir": "sk",
        "_prompt": "auto",
        "_correct": "voiture",
        "_mode": "plain"
      },
      {
        "lemma": "ulica",
        "fr": "rue",
        "gender": "F",
        "plural": "ulice",
        "example": "Na akej ulici bývaš?",
        "tip": "na ulici = dans la rue",
        "box": 0,
        "reviews": 0,
        "errors": 0
      },
      {
        "lemma": "obchod",
        "fr": "magasin",
        "gender": "M",
        "plural": "obchody",
        "example": "Idem do obchodu.",
        "tip": "do + génitif",
        "box": 0,
        "reviews": 0,
        "errors": 0,
        "_dir": "fr",
        "_prompt": "magasin",
        "_correct": "obchod",
        "_mode": "plain"
      },
      {
        "lemma": "práca",
        "fr": "travail",
        "gender": "F",
        "plural": "práce",
        "example": "Som v práci.",
        "tip": "pracovať = travailler",
        "box": 0,
        "reviews": 0,
        "errors": 0
      },
      {
        "lemma": "peniaze",
        "fr": "argent",
        "gender": "M",
        "plural": "(pluriel)",
        "example": "Nemám peniaze.",
        "tip": "Toujours au pluriel",
        "box": 0,
        "reviews": 0,
        "errors": 0
      },
      {
        "lemma": "telefón",
        "fr": "téléphone",
        "gender": "M",
        "plural": "telefóny",
        "example": "Kde je môj telefón?",
        "tip": "môj = mon",
        "box": 0,
        "reviews": 0,
        "errors": 0
      },
      {
        "lemma": "priateľ",
        "fr": "ami",
        "gender": "M",
        "plural": "priatelia",
        "example": "To je môj priateľ.",
        "tip": "priateľka = amie",
        "box": 0,
        "reviews": 0,
        "errors": 0
      },
      {
        "lemma": "sestra",
        "fr": "soeur",
        "gender": "F",
        "plural": "sestry",
        "example": "Mám dve sestry.",
        "tip": "dve = deux (f)",
        "box": 0,
        "reviews": 0,
        "errors": 0
      },
      {
        "lemma": "brat",
        "fr": "frère",
        "gender": "M",
        "plural": "bratia",
        "example": "Môj brat je starší.",
        "tip": "starší = plus vieux",
        "box": 0,
        "reviews": 0,
        "errors": 0,
        "_dir": "fr",
        "_prompt": "frère",
        "_correct": "brat",
        "_mode": "plain"
      },
      {
        "lemma": "škola",
        "fr": "école",
        "gender": "F",
        "plural": "školy",
        "example": "Idem do školy.",
        "tip": "do školy (génitif)",
        "box": 0,
        "reviews": 0,
        "errors": 0
      },
      {
        "lemma": "lekáreň",
        "fr": "pharmacie",
        "gender": "F",
        "plural": "lekárne",
        "example": "Kde je lekáreň?",
        "tip": "lekár = médecin",
        "box": 0,
        "reviews": 0,
        "errors": 0
      },
      {
        "lemma": "čas",
        "fr": "temps",
        "gender": "M",
        "plural": "časy",
        "example": "Nemám čas.",
        "tip": "Koľko je hodín? = Quelle heure ?",
        "box": 0,
        "reviews": 0,
        "errors": 0
      }
    ],
    "conjunction": [
      {
        "lemma": "a",
        "fr": "et",
        "example": "Ja a ty. = Moi et toi.",
        "tip": "Le plus simple",
        "box": 1,
        "reviews": 1,
        "errors": 0,
        "lastReview": 1773820457660
      },
      {
        "lemma": "ale",
        "fr": "mais",
        "example": "Chcem, ale nemôžem.",
        "tip": "Opposition",
        "box": 1,
        "reviews": 1,
        "errors": 0,
        "lastReview": 1773820462826
      },
      {
        "lemma": "alebo",
        "fr": "ou",
        "example": "Kávu alebo čaj?",
        "tip": "Choix",
        "box": 1,
        "reviews": 1,
        "errors": 0,
        "lastReview": 1773820471125
      },
      {
        "lemma": "pretože",
        "fr": "parce que",
        "example": "Nejdem, pretože som chorý.",
        "tip": "Cause",
        "box": 1,
        "reviews": 1,
        "errors": 0,
        "lastReview": 1773820477045
      },
      {
        "lemma": "preto",
        "fr": "c'est pourquoi",
        "example": "Preto som tu.",
        "tip": "Conséquence",
        "box": 2,
        "reviews": 3,
        "errors": 1,
        "lastReview": 1773833879109
      },
      {
        "lemma": "teda",
        "fr": "donc",
        "example": "Teda čo robíme?",
        "tip": "Conclusion",
        "box": 1,
        "reviews": 1,
        "errors": 0,
        "lastReview": 1773820484975
      },
      {
        "lemma": "tak",
        "fr": "alors",
        "example": "Tak poď!",
        "tip": "Très oral",
        "box": 1,
        "reviews": 1,
        "errors": 0,
        "lastReview": 1773820488794
      },
      {
        "lemma": "ak",
        "fr": "si",
        "example": "Ak chceš, poď.",
        "tip": "Condition",
        "box": 1,
        "reviews": 1,
        "errors": 0,
        "lastReview": 1773820491542
      },
      {
        "lemma": "keď",
        "fr": "quand",
        "example": "Keď prídeš, zavolaj.",
        "tip": "Temps + condition",
        "box": 1,
        "reviews": 1,
        "errors": 0,
        "lastReview": 1773820495694
      },
      {
        "lemma": "keby",
        "fr": "si (conditionnel)",
        "example": "Keby som vedel...",
        "tip": "Irréel",
        "box": 0,
        "reviews": 1,
        "errors": 1,
        "lastReview": 1773820499228
      },
      {
        "lemma": "však",
        "fr": "cependant",
        "example": "Však to nie je pravda.",
        "tip": "Plus formel que ale",
        "box": 0,
        "reviews": 2,
        "errors": 2,
        "lastReview": 1773820503526
      },
      {
        "lemma": "aj keď",
        "fr": "même si",
        "example": "Aj keď prší, ideme.",
        "tip": "Concession",
        "box": 0,
        "reviews": 0,
        "errors": 0
      },
      {
        "lemma": "ani",
        "fr": "même pas",
        "example": "Ani neviem.",
        "tip": "Négation renforcée",
        "box": 0,
        "reviews": 0,
        "errors": 0
      },
      {
        "lemma": "že",
        "fr": "que",
        "example": "Myslím, že áno.",
        "tip": "Subordonnant principal",
        "box": 0,
        "reviews": 0,
        "errors": 0
      },
      {
        "lemma": "aby",
        "fr": "pour que",
        "example": "Prišiel som, aby som ti pomohol.",
        "tip": "But + passé",
        "box": 0,
        "reviews": 0,
        "errors": 0
      },
      {
        "lemma": "hoci",
        "fr": "bien que",
        "example": "Hoci je mladý, je múdry.",
        "tip": "Concession formelle",
        "box": 0,
        "reviews": 1,
        "errors": 1,
        "lastReview": 1773820306717
      },
      {
        "lemma": "takže",
        "fr": "de sorte que",
        "example": "Takže idú domov.",
        "tip": "Conséquence",
        "box": 0,
        "reviews": 0,
        "errors": 0
      },
      {
        "lemma": "najprv",
        "fr": "d'abord",
        "example": "Najprv sa naješ, potom ideš.",
        "tip": "Séquence",
        "box": 0,
        "reviews": 0,
        "errors": 0
      },
      {
        "lemma": "potom",
        "fr": "ensuite",
        "example": "Potom ideme domov.",
        "tip": "Très fréquent",
        "box": 0,
        "reviews": 0,
        "errors": 0
      },
      {
        "lemma": "nakoniec",
        "fr": "finalement",
        "example": "Nakoniec sme to zvládli.",
        "tip": "Conclusion",
        "box": 0,
        "reviews": 1,
        "errors": 1,
        "lastReview": 1773820345978
      }
    ],
    "adjective": [
      {
        "lemma": "dobrý",
        "fr": "bon",
        "gender": "M/F/N: dobrý/á/é",
        "example": "To je dobré.",
        "tip": "dobre = bien",
        "box": 0,
        "reviews": 0,
        "errors": 0
      },
      {
        "lemma": "zlý",
        "fr": "mauvais",
        "gender": "M/F/N: zlý/á/é",
        "example": "Zlé počasie.",
        "tip": "zle = mal",
        "box": 0,
        "reviews": 0,
        "errors": 0
      },
      {
        "lemma": "veľký",
        "fr": "grand",
        "gender": "M/F/N: veľký/á/é",
        "example": "Veľký dom.",
        "tip": "veľmi = très",
        "box": 0,
        "reviews": 0,
        "errors": 0
      },
      {
        "lemma": "malý",
        "fr": "petit",
        "gender": "M/F/N: malý/á/é",
        "example": "Malé dieťa.",
        "tip": "",
        "box": 0,
        "reviews": 0,
        "errors": 0
      },
      {
        "lemma": "krásny",
        "fr": "beau/belle",
        "gender": "M/F/N: krásny/a/e",
        "example": "Si krásna.",
        "tip": "Pour ta copine !",
        "box": 0,
        "reviews": 0,
        "errors": 0
      },
      {
        "lemma": "nový",
        "fr": "nouveau",
        "gender": "M/F/N: nový/á/é",
        "example": "Nové auto.",
        "tip": "starý = opposé",
        "box": 0,
        "reviews": 0,
        "errors": 0
      },
      {
        "lemma": "starý",
        "fr": "vieux",
        "gender": "M/F/N: starý/á/é",
        "example": "Staré mesto.",
        "tip": "Bratislava Staré Mesto !",
        "box": 0,
        "reviews": 0,
        "errors": 0
      },
      {
        "lemma": "mladý",
        "fr": "jeune",
        "gender": "M/F/N: mladý/á/é",
        "example": "Mladá žena.",
        "tip": "",
        "box": 0,
        "reviews": 0,
        "errors": 0
      },
      {
        "lemma": "drahý",
        "fr": "cher",
        "gender": "M/F/N: drahý/á/é",
        "example": "To je príliš drahé.",
        "tip": "príliš = trop",
        "box": 0,
        "reviews": 0,
        "errors": 0
      },
      {
        "lemma": "lacný",
        "fr": "pas cher",
        "gender": "M/F/N: lacný/á/é",
        "example": "To je lacné.",
        "tip": "",
        "box": 0,
        "reviews": 0,
        "errors": 0
      },
      {
        "lemma": "teplý",
        "fr": "chaud",
        "gender": "M/F/N: teplý/á/é",
        "example": "Teplá káva.",
        "tip": "teplo = il fait chaud",
        "box": 0,
        "reviews": 0,
        "errors": 0
      },
      {
        "lemma": "studený",
        "fr": "froid",
        "gender": "M/F/N: studený/á/é",
        "example": "Studená voda.",
        "tip": "zima = froid/hiver",
        "box": 0,
        "reviews": 0,
        "errors": 0
      },
      {
        "lemma": "dlhý",
        "fr": "long",
        "gender": "M/F/N: dlhý/á/é",
        "example": "Dlhá cesta.",
        "tip": "",
        "box": 0,
        "reviews": 0,
        "errors": 0
      },
      {
        "lemma": "krátky",
        "fr": "court",
        "gender": "M/F/N: krátky/a/e",
        "example": "Krátky čas.",
        "tip": "",
        "box": 0,
        "reviews": 0,
        "errors": 0
      },
      {
        "lemma": "ťažký",
        "fr": "difficile",
        "gender": "M/F/N: ťažký/á/é",
        "example": "To je ťažké.",
        "tip": "Aussi = lourd",
        "box": 0,
        "reviews": 0,
        "errors": 0
      },
      {
        "lemma": "ľahký",
        "fr": "facile",
        "gender": "M/F/N: ľahký/á/é",
        "example": "To je ľahké.",
        "tip": "",
        "box": 0,
        "reviews": 0,
        "errors": 0
      },
      {
        "lemma": "rýchly",
        "fr": "rapide",
        "gender": "M/F/N: rýchly/a/e",
        "example": "Rýchle auto.",
        "tip": "rýchlo = vite",
        "box": 0,
        "reviews": 0,
        "errors": 0
      },
      {
        "lemma": "pomalý",
        "fr": "lent",
        "gender": "M/F/N: pomalý/á/é",
        "example": "Hovorte pomalšie.",
        "tip": "pomalšie = comparatif",
        "box": 0,
        "reviews": 0,
        "errors": 0
      },
      {
        "lemma": "šťastný",
        "fr": "heureux",
        "gender": "M/F/N: šťastný/á/é",
        "example": "Som šťastný.",
        "tip": "šťastie = bonheur",
        "box": 0,
        "reviews": 0,
        "errors": 0
      },
      {
        "lemma": "smutný",
        "fr": "triste",
        "gender": "M/F/N: smutný/á/é",
        "example": "Prečo si smutná?",
        "tip": "",
        "box": 0,
        "reviews": 0,
        "errors": 0
      }
    ],
    "pronoun": [
      {
        "lemma": "ja",
        "fr": "je/moi",
        "example": "Ja som tu. = Je suis là.",
        "tip": "Souvent omis",
        "box": 0,
        "reviews": 0,
        "errors": 0
      },
      {
        "lemma": "ty",
        "fr": "tu/toi",
        "example": "Ty si krásna.",
        "tip": "Informel",
        "box": 0,
        "reviews": 0,
        "errors": 0
      },
      {
        "lemma": "on",
        "fr": "il/lui",
        "example": "On je doma.",
        "tip": "",
        "box": 0,
        "reviews": 0,
        "errors": 0
      },
      {
        "lemma": "ona",
        "fr": "elle",
        "example": "Ona pracuje.",
        "tip": "",
        "box": 0,
        "reviews": 0,
        "errors": 0
      },
      {
        "lemma": "to",
        "fr": "c'est / ça",
        "example": "To je dobré.",
        "tip": "Démonstratif neutre",
        "box": 0,
        "reviews": 0,
        "errors": 0
      },
      {
        "lemma": "my",
        "fr": "nous",
        "example": "My ideme.",
        "tip": "",
        "box": 0,
        "reviews": 0,
        "errors": 0,
        "_dir": "fr",
        "_prompt": "nous",
        "_correct": "my",
        "_mode": "plain"
      },
      {
        "lemma": "vy",
        "fr": "vous",
        "example": "Vy ste učiteľ.",
        "tip": "Aussi vouvoiement",
        "box": 0,
        "reviews": 0,
        "errors": 0
      },
      {
        "lemma": "oni",
        "fr": "ils/eux",
        "example": "Oni idú.",
        "tip": "ony = elles",
        "box": 0,
        "reviews": 0,
        "errors": 0
      },
      {
        "lemma": "kto",
        "fr": "qui",
        "example": "Kto je to?",
        "tip": "Question",
        "box": 0,
        "reviews": 0,
        "errors": 0
      },
      {
        "lemma": "čo",
        "fr": "quoi/que",
        "example": "Čo chceš?",
        "tip": "Question essentielle",
        "box": 0,
        "reviews": 0,
        "errors": 0
      },
      {
        "lemma": "ten/tá/to",
        "fr": "ce/cette/cela",
        "example": "Ten dom je veľký.",
        "tip": "M/F/N: ten/tá/to",
        "box": 0,
        "reviews": 0,
        "errors": 0
      },
      {
        "lemma": "môj/moja",
        "fr": "mon/ma",
        "example": "Môj dom. Moja sestra.",
        "tip": "M/F: môj/moja/moje",
        "box": 0,
        "reviews": 0,
        "errors": 0
      },
      {
        "lemma": "tvoj/tvoja",
        "fr": "ton/ta",
        "example": "Tvoj telefón. Tvoja káva.",
        "tip": "M/F: tvoj/tvoja/tvoje",
        "box": 0,
        "reviews": 0,
        "errors": 0
      },
      {
        "lemma": "jeho",
        "fr": "son/sa (à lui)",
        "example": "Jeho auto.",
        "tip": "Invariable !",
        "box": 0,
        "reviews": 0,
        "errors": 0
      },
      {
        "lemma": "jej",
        "fr": "son/sa (à elle)",
        "example": "Jej sestra.",
        "tip": "Invariable !",
        "box": 0,
        "reviews": 0,
        "errors": 0
      }
    ],
    "preposition": [
      {
        "lemma": "v/vo",
        "fr": "dans/en",
        "example": "Som v práci.",
        "tip": "vo devant v-,f-",
        "grammar_note": "+ locatif",
        "box": 0,
        "reviews": 0,
        "errors": 0
      },
      {
        "lemma": "na",
        "fr": "sur/à",
        "example": "Na stole. Na Slovensku.",
        "tip": "Surface ou destination",
        "grammar_note": "+ locatif ou accusatif",
        "box": 0,
        "reviews": 0,
        "errors": 0
      },
      {
        "lemma": "do",
        "fr": "dans/vers",
        "example": "Idem do obchodu.",
        "tip": "Direction",
        "grammar_note": "+ génitif",
        "box": 0,
        "reviews": 0,
        "errors": 0
      },
      {
        "lemma": "z/zo",
        "fr": "de/depuis",
        "example": "Som z Francúzska.",
        "tip": "Origine",
        "grammar_note": "+ génitif",
        "box": 0,
        "reviews": 0,
        "errors": 0
      },
      {
        "lemma": "s/so",
        "fr": "avec",
        "example": "Pôjdem s tebou.",
        "tip": "so devant s-,z-,š-,ž-",
        "grammar_note": "+ instrumental",
        "box": 0,
        "reviews": 0,
        "errors": 0
      },
      {
        "lemma": "od",
        "fr": "de/depuis",
        "example": "Od rána.",
        "tip": "Point de départ",
        "grammar_note": "+ génitif",
        "box": 0,
        "reviews": 0,
        "errors": 0
      },
      {
        "lemma": "pri",
        "fr": "près de",
        "example": "Pri stole.",
        "tip": "Proximité",
        "grammar_note": "+ locatif",
        "box": 0,
        "reviews": 0,
        "errors": 0
      },
      {
        "lemma": "o",
        "fr": "à propos de",
        "example": "O čom hovoríš?",
        "tip": "o pätej = à 5h",
        "grammar_note": "+ locatif",
        "box": 0,
        "reviews": 0,
        "errors": 0
      },
      {
        "lemma": "pre",
        "fr": "pour",
        "example": "To je pre teba.",
        "tip": "Bénéficiaire",
        "grammar_note": "+ accusatif",
        "box": 0,
        "reviews": 0,
        "errors": 0
      },
      {
        "lemma": "bez",
        "fr": "sans",
        "example": "Bez cukru.",
        "tip": "",
        "grammar_note": "+ génitif",
        "box": 1,
        "reviews": 1,
        "errors": 0,
        "lastReview": 1773820325729
      },
      {
        "lemma": "k/ku",
        "fr": "vers/chez",
        "example": "Idem k lekárovi.",
        "tip": "ku devant k-,g-",
        "grammar_note": "+ datif",
        "box": 0,
        "reviews": 0,
        "errors": 0
      },
      {
        "lemma": "za",
        "fr": "derrière/pour",
        "example": "Za koľko?",
        "tip": "Double sens",
        "grammar_note": "+ accusatif ou instrumental",
        "box": 0,
        "reviews": 0,
        "errors": 0
      },
      {
        "lemma": "po",
        "fr": "après/le long de",
        "example": "Po slovensky.",
        "tip": "po + langue",
        "grammar_note": "+ locatif",
        "box": 0,
        "reviews": 0,
        "errors": 0
      },
      {
        "lemma": "pred",
        "fr": "devant/avant",
        "example": "Pred domom.",
        "tip": "Spatial ou temporel",
        "grammar_note": "+ instrumental",
        "box": 0,
        "reviews": 0,
        "errors": 0
      },
      {
        "lemma": "medzi",
        "fr": "entre",
        "example": "Medzi nami.",
        "tip": "",
        "grammar_note": "+ instrumental",
        "box": 0,
        "reviews": 0,
        "errors": 0
      }
    ],
    "adverb": [
      {
        "lemma": "tu",
        "fr": "ici",
        "example": "Som tu.",
        "tip": "Position",
        "box": 0,
        "reviews": 0,
        "errors": 0
      },
      {
        "lemma": "tam",
        "fr": "là-bas",
        "example": "Ideme tam.",
        "tip": "Direction aussi",
        "box": 0,
        "reviews": 0,
        "errors": 0
      },
      {
        "lemma": "teraz",
        "fr": "maintenant",
        "example": "Teraz nemôžem.",
        "tip": "Très fréquent",
        "box": 0,
        "reviews": 0,
        "errors": 0
      },
      {
        "lemma": "dnes",
        "fr": "aujourd'hui",
        "example": "Čo robíme dnes?",
        "tip": "",
        "box": 0,
        "reviews": 0,
        "errors": 0
      },
      {
        "lemma": "zajtra",
        "fr": "demain",
        "example": "Zajtra ráno.",
        "tip": "ráno = matin",
        "box": 0,
        "reviews": 0,
        "errors": 0
      },
      {
        "lemma": "včera",
        "fr": "hier",
        "example": "Včera som bol doma.",
        "tip": "bol/bola = j'étais",
        "box": 0,
        "reviews": 0,
        "errors": 0
      },
      {
        "lemma": "veľmi",
        "fr": "très/beaucoup",
        "example": "Veľmi ďakujem.",
        "tip": "Intensificateur #1",
        "box": 0,
        "reviews": 0,
        "errors": 0
      },
      {
        "lemma": "ešte",
        "fr": "encore",
        "example": "Ešte raz.",
        "tip": "raz = fois",
        "box": 0,
        "reviews": 0,
        "errors": 0
      },
      {
        "lemma": "už",
        "fr": "déjà",
        "example": "Už idem.",
        "tip": "",
        "box": 0,
        "reviews": 0,
        "errors": 0
      },
      {
        "lemma": "asi",
        "fr": "peut-être",
        "example": "Asi áno.",
        "tip": "Incertitude",
        "box": 0,
        "reviews": 0,
        "errors": 0
      },
      {
        "lemma": "dobre",
        "fr": "bien",
        "example": "To je dobre.",
        "tip": "dobrý = bon (adj)",
        "box": 0,
        "reviews": 0,
        "errors": 0
      },
      {
        "lemma": "vždy",
        "fr": "toujours",
        "example": "Vždy si krásna.",
        "tip": "",
        "box": 0,
        "reviews": 0,
        "errors": 0
      },
      {
        "lemma": "nikdy",
        "fr": "jamais",
        "example": "Nikdy nehovor nikdy.",
        "tip": "Double négation en SK !",
        "box": 0,
        "reviews": 0,
        "errors": 0
      },
      {
        "lemma": "rýchlo",
        "fr": "vite",
        "example": "Poď rýchlo!",
        "tip": "rýchly = rapide",
        "box": 0,
        "reviews": 0,
        "errors": 0
      },
      {
        "lemma": "pomaly",
        "fr": "lentement",
        "example": "Hovorte pomaly.",
        "tip": "pomalšie = plus lentement",
        "box": 0,
        "reviews": 0,
        "errors": 0
      }
    ],
    "number": [
      {
        "lemma": "jeden/jedna/jedno",
        "fr": "un/une",
        "example": "Jeden čaj, prosím.",
        "tip": "M/F/N",
        "box": 1,
        "reviews": 1,
        "errors": 0,
        "lastReview": 1773820516257
      },
      {
        "lemma": "dva/dve",
        "fr": "deux",
        "example": "Dve pivá, prosím.",
        "tip": "dva (M), dve (F/N)",
        "box": 1,
        "reviews": 1,
        "errors": 0,
        "lastReview": 1773820518909
      },
      {
        "lemma": "tri",
        "fr": "trois",
        "example": "Tri deti.",
        "tip": "",
        "box": 0,
        "reviews": 0,
        "errors": 0
      },
      {
        "lemma": "štyri",
        "fr": "quatre",
        "example": "Štyri hodiny.",
        "tip": "",
        "box": 0,
        "reviews": 0,
        "errors": 0
      },
      {
        "lemma": "päť",
        "fr": "cinq",
        "example": "Päť eur.",
        "tip": "Après 5 → génitif pluriel",
        "box": 0,
        "reviews": 0,
        "errors": 0
      },
      {
        "lemma": "šesť",
        "fr": "six",
        "example": "Šesť hodín.",
        "tip": "",
        "box": 0,
        "reviews": 0,
        "errors": 0
      },
      {
        "lemma": "sedem",
        "fr": "sept",
        "example": "",
        "tip": "",
        "box": 0,
        "reviews": 0,
        "errors": 0
      },
      {
        "lemma": "osem",
        "fr": "huit",
        "example": "",
        "tip": "",
        "box": 0,
        "reviews": 0,
        "errors": 0
      },
      {
        "lemma": "deväť",
        "fr": "neuf",
        "example": "",
        "tip": "",
        "box": 0,
        "reviews": 0,
        "errors": 0
      },
      {
        "lemma": "desať",
        "fr": "dix",
        "example": "Desať minút.",
        "tip": "",
        "box": 0,
        "reviews": 0,
        "errors": 0
      },
      {
        "lemma": "sto",
        "fr": "cent",
        "example": "Sto eur.",
        "tip": "",
        "box": 0,
        "reviews": 0,
        "errors": 0
      },
      {
        "lemma": "tisíc",
        "fr": "mille",
        "example": "Tisíc eur.",
        "tip": "",
        "box": 0,
        "reviews": 0,
        "errors": 0
      }
    ],
    "expression": [
      {
        "lemma": "Dobrý deň!",
        "fr": "Bonjour ! (formel)",
        "example": "Dobrý deň, ako sa máte?",
        "tip": "Formel",
        "box": 0,
        "reviews": 0,
        "errors": 0
      },
      {
        "lemma": "Ahoj!",
        "fr": "Salut !",
        "example": "Ahoj, ako sa máš?",
        "tip": "Informel",
        "box": 0,
        "reviews": 0,
        "errors": 0
      },
      {
        "lemma": "Ďakujem",
        "fr": "Merci",
        "example": "Ďakujem veľmi pekne.",
        "tip": "pekne = joliment",
        "box": 0,
        "reviews": 0,
        "errors": 0
      },
      {
        "lemma": "Prosím",
        "fr": "SVP / De rien",
        "example": "Prosím? = Pardon ?",
        "tip": "Double sens !",
        "box": 0,
        "reviews": 0,
        "errors": 0
      },
      {
        "lemma": "Prepáčte",
        "fr": "Excusez-moi",
        "example": "Prepáč(te), kde je...?",
        "tip": "Prepáč = informel",
        "box": 0,
        "reviews": 0,
        "errors": 0
      },
      {
        "lemma": "Ako sa máš?",
        "fr": "Comment vas-tu ?",
        "example": "Ako sa máš? Dobre!",
        "tip": "mať sa = aller (état)",
        "box": 0,
        "reviews": 0,
        "errors": 0
      },
      {
        "lemma": "Dobre, ďakujem",
        "fr": "Bien, merci",
        "example": "Dobre, ďakujem, a ty?",
        "tip": "Réponse classique",
        "box": 0,
        "reviews": 0,
        "errors": 0
      },
      {
        "lemma": "Na zdravie!",
        "fr": "Santé ! / À tes souhaits !",
        "example": "Na zdravie! (trinquer)",
        "tip": "Trinquer ET éternuement",
        "box": 0,
        "reviews": 0,
        "errors": 0
      },
      {
        "lemma": "Dovidenia!",
        "fr": "Au revoir !",
        "example": "Dovidenia, pekný deň!",
        "tip": "Formel",
        "box": 0,
        "reviews": 0,
        "errors": 0
      },
      {
        "lemma": "Dobrú noc",
        "fr": "Bonne nuit",
        "example": "Dobrú noc, zlatko.",
        "tip": "zlatko = chéri(e)",
        "box": 0,
        "reviews": 0,
        "errors": 0
      },
      {
        "lemma": "Koľko to stojí?",
        "fr": "Combien ça coûte ?",
        "example": "Koľko to stojí? Päť eur.",
        "tip": "Magasin / restaurant",
        "box": 0,
        "reviews": 0,
        "errors": 0
      },
      {
        "lemma": "Nerozumiem",
        "fr": "Je ne comprends pas",
        "example": "Prepáčte, nerozumiem.",
        "tip": "Survie #1",
        "box": 0,
        "reviews": 0,
        "errors": 0
      },
      {
        "lemma": "Hovorte pomalšie",
        "fr": "Parlez plus lentement",
        "example": "Prosím, hovorte pomalšie.",
        "tip": "",
        "box": 0,
        "reviews": 0,
        "errors": 0
      },
      {
        "lemma": "Kde je...?",
        "fr": "Où est... ?",
        "example": "Kde je toaleta?",
        "tip": "Question clé",
        "box": 0,
        "reviews": 0,
        "errors": 0
      },
      {
        "lemma": "Milujem ťa",
        "fr": "Je t'aime",
        "example": "Milujem ťa, láska.",
        "tip": "láska = amour",
        "box": 0,
        "reviews": 0,
        "errors": 0
      },
      {
        "lemma": "Chýbaš mi",
        "fr": "Tu me manques",
        "example": "Veľmi mi chýbaš.",
        "tip": "chýbať = manquer",
        "box": 0,
        "reviews": 0,
        "errors": 0
      },
      {
        "lemma": "Všetko najlepšie!",
        "fr": "Bon anniversaire !",
        "example": "Všetko najlepšie k narodeninám!",
        "tip": "Lit: tout le meilleur",
        "box": 0,
        "reviews": 0,
        "errors": 0
      },
      {
        "lemma": "Daj mi pusu",
        "fr": "Donne-moi un bisou",
        "example": "Daj mi pusu!",
        "tip": "pusa = bisou",
        "box": 0,
        "reviews": 0,
        "errors": 0
      },
      {
        "lemma": "Poďme!",
        "fr": "Allons-y !",
        "example": "Poďme do kina!",
        "tip": "kino = cinéma",
        "box": 0,
        "reviews": 0,
        "errors": 0
      },
      {
        "lemma": "Teším sa na teba",
        "fr": "J'ai hâte de te voir",
        "example": "Teším sa na teba, láska.",
        "tip": "tešiť sa na = se réjouir",
        "box": 0,
        "reviews": 0,
        "errors": 0
      }
    ]
  }
}